gpgdo/gpgdo.py
gpgdo-1.0.2.dist-info/AUTHORS
gpgdo-1.0.2.dist-info/LICENSE
gpgdo-1.0.2.dist-info/METADATA
gpgdo-1.0.2.dist-info/WHEEL
gpgdo-1.0.2.dist-info/entry_points.txt
gpgdo-1.0.2.dist-info/top_level.txt
gpgdo-1.0.2.dist-info/RECORD
