Metadata-Version: 2.1
Name: gpgdo
Version: 1.0.2
Summary: gpgdo decreases effort of using gpg encrypted files
Author-email: Heikki Orsila <heikki.orsila@iki.fi>
License-File: LICENSE
License-File: AUTHORS
